MANIFEST.in
README.md
pyproject.toml
setup.py
pubsub_proxy/__init__.py
pubsub_proxy/daemon.py
pubsub_proxy/events.py
pubsub_proxy/progress_storage.py
pubsub_proxy/proxy.py
pubsub_proxy/pubsub_adapter.py
pubsub_proxy/settings.py
pubsub_proxy/subscription_storage.py
pubsub_proxy/util.py
pubsub_proxy.egg-info/PKG-INFO
pubsub_proxy.egg-info/SOURCES.txt
pubsub_proxy.egg-info/dependency_links.txt
pubsub_proxy.egg-info/entry_points.txt
pubsub_proxy.egg-info/requires.txt
pubsub_proxy.egg-info/top_level.txt
pubsub_proxy.egg-info/zip-safe
pubsub_proxy/proto/__init__.py
pubsub_proxy/proto/access_path.proto
pubsub_proxy/proto/account_state_blob.proto
pubsub_proxy/proto/admission_control.proto
pubsub_proxy/proto/events.proto
pubsub_proxy/proto/fix.sh
pubsub_proxy/proto/get_with_proof.proto
pubsub_proxy/proto/language_storage.proto
pubsub_proxy/proto/ledger_info.proto
pubsub_proxy/proto/mempool_status.proto
pubsub_proxy/proto/proof.proto
pubsub_proxy/proto/transaction.proto
pubsub_proxy/proto/transaction_info.proto
pubsub_proxy/proto/validator_change.proto
pubsub_proxy/proto/validator_public_keys.proto
pubsub_proxy/proto/validator_set.proto
pubsub_proxy/proto/vm_errors.proto