Metadata-Version: 1.2
Name: pubsub-proxy
Version: 0.1.3
Summary: A Libra pub/sub proxy
Home-page: https://github.com/calibra/pubsub_proxy
License: UNKNOWN
Platform: UNKNOWN
Requires-Python: ~=3.7
